README.rst
setup.py
twitterbot_farm/__init__.py
twitterbot_farm/analyzer.py
twitterbot_farm/bot.py
twitterbot_farm/reader.py
twitterbot_farm/writer.py
twitterbot_farm.egg-info/PKG-INFO
twitterbot_farm.egg-info/SOURCES.txt
twitterbot_farm.egg-info/dependency_links.txt
twitterbot_farm.egg-info/requires.txt
twitterbot_farm.egg-info/top_level.txt
utils/tfctl
utils/tfctl.py