Metadata-Version: 1.1
Name: twitterbot-farm
Version: 0.2.1
Summary: "Framework" for running a lot of twitterbots without useless twitter API calls.
Home-page: https://github.com/strizhechenko/twitterbot_farm
Author: Oleg Strizhechenko
Author-email: oleg.strizhechenko@gmail.com
License: GPL
Keywords: twitter api bot farm
Platform: UNKNOWN
Classifier: Development Status :: 3 - Alpha
Classifier: Intended Audience :: Developers
Classifier: Operating System :: MacOS
Classifier: Operating System :: POSIX
Classifier: Programming Language :: Python
Classifier: Programming Language :: Python :: 2
Classifier: Topic :: Software Development
Classifier: Topic :: Utilities
